serv/__init__.py
serv/add_user.py
serv/config_window.py
serv/core.py
serv/database.py
serv/main_window.py
serv/remove_user.py
serv/stat_window.py
server_chat_pyqt_motr-0.1.dist-info/METADATA
server_chat_pyqt_motr-0.1.dist-info/WHEEL
server_chat_pyqt_motr-0.1.dist-info/top_level.txt
server_chat_pyqt_motr-0.1.dist-info/RECORD
