Metadata-Version: 2.1
Name: server_chat_pyqt_motr
Version: 0.1
Summary: Server packet
Author: Roman Motrich
Author-email: test@mail.ru
License: UNKNOWN
Platform: UNKNOWN
